{"cols":[{"type":"date"},{"type":"number"}],"rows":[{"c":[{"v":"Date(2015,01,05)"},{"v":"1483.25\r\n"}]},{"c":[{"v":"Date(2015,01,06)"},{"v":"1477.58\r\n"}]},{"c":[{"v":"Date(2015,01,07)"},{"v":"1500.75\r\n"}]},{"c":[{"v":"Date(2015,01,08)"},{"v":"1521.62\r\n"}]},{"c":[{"v":"Date(2015,01,09)"},{"v":"1529.42\r\n"}]},{"c":[{"v":"Date(2015,01,12)"},{"v":"1531.21\r\n"}]},{"c":[{"v":"Date(2015,01,13)"},{"v":"1534.97\r\n"}]},{"c":[{"v":"Date(2015,01,14)"},{"v":"1523.24\r\n"}]},{"c":[{"v":"Date(2015,01,15)"},{"v":"1523.38\r\n"}]},{"c":[{"v":"Date(2015,01,16)"},{"v":"1517.74\r\n"}]},{"c":[{"v":"Date(2015,01,19)"},{"v":"1535.37\r\n"}]},{"c":[{"v":"Date(2015,01,20)"},{"v":"1535.09\r\n"}]},{"c":[{"v":"Date(2015,01,21)"},{"v":"1537.36\r\n"}]},{"c":[{"v":"Date(2015,01,22)"},{"v":"1560.34\r\n"}]},{"c":[{"v":"Date(2015,01,23)"},{"v":"1598.33\r\n"}]},{"c":[{"v":"Date(2015,01,26)"},{"v":"1588.31\r\n"}]},{"c":[{"v":"Date(2015,01,27)"},{"v":"1589.81\r\n"}]},{"c":[{"v":"Date(2015,01,28)"},{"v":"1592.81\r\n"}]},{"c":[{"v":"Date(2015,01,29)"},{"v":"1586.4\r\n"}]},{"c":[{"v":"Date(2015,01,30)"},{"v":"1581.25\r\n"}]},{"c":[{"v":"Date(2015,02,02)"},{"v":"1582.7\r\n"}]},{"c":[{"v":"Date(2015,02,03)"},{"v":"1602.54\r\n"}]},{"c":[{"v":"Date(2015,02,04)"},{"v":"1599.81\r\n"}]},{"c":[{"v":"Date(2015,02,05)"},{"v":"1607.92\r\n"}]},{"c":[{"v":"Date(2015,02,06)"},{"v":"1613.63\r\n"}]},{"c":[{"v":"Date(2015,02,09)"},{"v":"1601.77\r\n"}]},{"c":[{"v":"Date(2015,02,10)"},{"v":"1594.96\r\n"}]},{"c":[{"v":"Date(2015,02,11)"},{"v":"1605.11\r\n"}]},{"c":[{"v":"Date(2015,02,12)"},{"v":"1613.4\r\n"}]},{"c":[{"v":"Date(2015,02,13)"},{"v":"1615.89\r\n"}]},{"c":[{"v":"Date(2015,02,16)"},{"v":"1608.04\r\n"}]},{"c":[{"v":"Date(2015,02,17)"},{"v":"1587.75\r\n"}]},{"c":[{"v":"Date(2015,02,18)"},{"v":"1603.14\r\n"}]},{"c":[{"v":"Date(2015,02,19)"},{"v":"1599.96\r\n"}]},{"c":[{"v":"Date(2015,02,20)"},{"v":"1603.45\r\n"}]},{"c":[{"v":"Date(2015,02,23)"},{"v":"1593.89\r\n"}]},{"c":[{"v":"Date(2015,02,24)"},{"v":"1598.66\r\n"}]},{"c":[{"v":"Date(2015,02,25)"},{"v":"1589.33\r\n"}]},{"c":[{"v":"Date(2015,02,26)"},{"v":"1593.55\r\n"}]},{"c":[{"v":"Date(2015,02,27)"},{"v":"1587.01\r\n"}]},{"c":[{"v":"Date(2015,03,02)"},{"v":"1582.14\r\n"}]},{"c":[{"v":"Date(2015,03,03)"},{"v":"1562.84\r\n"}]},{"c":[{"v":"Date(2015,03,05)"},{"v":"1553.33\r\n"}]},{"c":[{"v":"Date(2015,03,06)"},{"v":"1568.29\r\n"}]},{"c":[{"v":"Date(2015,03,09)"},{"v":"1559.71\r\n"}]},{"c":[{"v":"Date(2015,03,10)"},{"v":"1531.04\r\n"}]},{"c":[{"v":"Date(2015,03,11)"},{"v":"1543.84\r\n"}]},{"c":[{"v":"Date(2015,03,12)"},{"v":"1544.34\r\n"}]},{"c":[{"v":"Date(2015,03,13)"},{"v":"1541.55\r\n"}]},{"c":[{"v":"Date(2015,03,16)"},{"v":"1515.57\r\n"}]},{"c":[{"v":"Date(2015,03,17)"},{"v":"1512.84\r\n"}]},{"c":[{"v":"Date(2015,03,18)"},{"v":"1531.5\r\n"}]},{"c":[{"v":"Date(2015,03,19)"},{"v":"1532.13\r\n"}]},{"c":[{"v":"Date(2015,03,20)"},{"v":"1529.96\r\n"}]},{"c":[{"v":"Date(2015,03,23)"},{"v":"1520.01\r\n"}]},{"c":[{"v":"Date(2015,03,24)"},{"v":"1514.45\r\n"}]},{"c":[{"v":"Date(2015,03,25)"},{"v":"1512.8\r\n"}]},{"c":[{"v":"Date(2015,03,26)"},{"v":"1496.41\r\n"}]},{"c":[{"v":"Date(2015,03,27)"},{"v":"1495.22\r\n"}]},{"c":[{"v":"Date(2015,03,30)"},{"v":"1496.51\r\n"}]},{"c":[{"v":"Date(2015,03,31)"},{"v":"1505.94\r\n"}]},{"c":[{"v":"Date(2015,04,01)"},{"v":"1525.58\r\n"}]},{"c":[{"v":"Date(2015,04,02)"},{"v":"1532.23\r\n"}]},{"c":[{"v":"Date(2015,04,03)"},{"v":"1536.05\r\n"}]},{"c":[{"v":"Date(2015,04,07)"},{"v":"1549.53\r\n"}]},{"c":[{"v":"Date(2015,04,08)"},{"v":"1544.86\r\n"}]},{"c":[{"v":"Date(2015,04,09)"},{"v":"1545.11\r\n"}]},{"c":[{"v":"Date(2015,04,10)"},{"v":"1547.83\r\n"}]},{"c":[{"v":"Date(2015,04,16)"},{"v":"1570\r\n"}]},{"c":[{"v":"Date(2015,04,17)"},{"v":"1566.85\r\n"}]},{"c":[{"v":"Date(2015,04,20)"},{"v":"1560.32\r\n"}]},{"c":[{"v":"Date(2015,04,21)"},{"v":"1569.35\r\n"}]},{"c":[{"v":"Date(2015,04,22)"},{"v":"1552.01\r\n"}]},{"c":[{"v":"Date(2015,04,23)"},{"v":"1544.84\r\n"}]},{"c":[{"v":"Date(2015,04,24)"},{"v":"1555.46\r\n"}]},{"c":[{"v":"Date(2015,04,27)"},{"v":"1548.83\r\n"}]},{"c":[{"v":"Date(2015,04,28)"},{"v":"1531.53\r\n"}]},{"c":[{"v":"Date(2015,04,29)"},{"v":"1522.47\r\n"}]},{"c":[{"v":"Date(2015,04,30)"},{"v":"1526.74\r\n"}]},{"c":[{"v":"Date(2015,05,06)"},{"v":"1519.88\r\n"}]},{"c":[{"v":"Date(2015,05,07)"},{"v":"1498.31\r\n"}]},{"c":[{"v":"Date(2015,05,08)"},{"v":"1510.51\r\n"}]},{"c":[{"v":"Date(2015,05,11)"},{"v":"1501.3\r\n"}]},{"c":[{"v":"Date(2015,05,12)"},{"v":"1485.72\r\n"}]},{"c":[{"v":"Date(2015,05,13)"},{"v":"1495.95\r\n"}]},{"c":[{"v":"Date(2015,05,14)"},{"v":"1497.4\r\n"}]},{"c":[{"v":"Date(2015,05,15)"},{"v":"1512.19\r\n"}]},{"c":[{"v":"Date(2015,05,18)"},{"v":"1510.41\r\n"}]},{"c":[{"v":"Date(2015,05,19)"},{"v":"1525.96\r\n"}]},{"c":[{"v":"Date(2015,05,20)"},{"v":"1520.11\r\n"}]},{"c":[{"v":"Date(2015,05,21)"},{"v":"1526.25\r\n"}]},{"c":[{"v":"Date(2015,05,22)"},{"v":"1523.86\r\n"}]},{"c":[{"v":"Date(2015,05,25)"},{"v":"1508.16\r\n"}]},{"c":[{"v":"Date(2015,05,26)"},{"v":"1497.98\r\n"}]},{"c":[{"v":"Date(2015,05,27)"},{"v":"1500.84\r\n"}]},{"c":[{"v":"Date(2015,05,28)"},{"v":"1493.61\r\n"}]},{"c":[{"v":"Date(2015,05,29)"},{"v":"1496.05\r\n"}]},{"c":[{"v":"Date(2015,06,02)"},{"v":"1476.87\r\n"}]},{"c":[{"v":"Date(2015,06,03)"},{"v":"1482.07\r\n"}]},{"c":[{"v":"Date(2015,06,04)"},{"v":"1490.9\r\n"}]},{"c":[{"v":"Date(2015,06,05)"},{"v":"1507.37\r\n"}]},{"c":[{"v":"Date(2015,06,08)"},{"v":"1508.28\r\n"}]},{"c":[{"v":"Date(2015,06,09)"},{"v":"1492.32\r\n"}]},{"c":[{"v":"Date(2015,06,10)"},{"v":"1504.04\r\n"}]},{"c":[{"v":"Date(2015,06,11)"},{"v":"1514.81\r\n"}]},{"c":[{"v":"Date(2015,06,12)"},{"v":"1508.23\r\n"}]},{"c":[{"v":"Date(2015,06,15)"},{"v":"1501.89\r\n"}]},{"c":[{"v":"Date(2015,06,16)"},{"v":"1503.28\r\n"}]},{"c":[{"v":"Date(2015,06,17)"},{"v":"1514.79\r\n"}]},{"c":[{"v":"Date(2015,06,18)"},{"v":"1508.04\r\n"}]},{"c":[{"v":"Date(2015,06,19)"},{"v":"1491.46\r\n"}]},{"c":[{"v":"Date(2015,06,22)"},{"v":"1504.06\r\n"}]},{"c":[{"v":"Date(2015,06,23)"},{"v":"1503.23\r\n"}]},{"c":[{"v":"Date(2015,06,24)"},{"v":"1518.26\r\n"}]},{"c":[{"v":"Date(2015,06,25)"},{"v":"1519.47\r\n"}]},{"c":[{"v":"Date(2015,06,26)"},{"v":"1518.03\r\n"}]},{"c":[{"v":"Date(2015,06,29)"},{"v":"1511.19\r\n"}]},{"c":[{"v":"Date(2015,06,30)"},{"v":"1504.55\r\n"}]},{"c":[{"v":"Date(2015,07,02)"},{"v":"1491.62\r\n"}]},{"c":[{"v":"Date(2015,07,03)"},{"v":"1489.59\r\n"}]},{"c":[{"v":"Date(2015,07,06)"},{"v":"1473.23\r\n"}]},{"c":[{"v":"Date(2015,07,07)"},{"v":"1483.77\r\n"}]},{"c":[{"v":"Date(2015,07,08)"},{"v":"1470.25\r\n"}]},{"c":[{"v":"Date(2015,07,09)"},{"v":"1472.57\r\n"}]},{"c":[{"v":"Date(2015,07,10)"},{"v":"1484.9\r\n"}]},{"c":[{"v":"Date(2015,07,13)"},{"v":"1490.65\r\n"}]},{"c":[{"v":"Date(2015,07,14)"},{"v":"1488.4\r\n"}]},{"c":[{"v":"Date(2015,07,15)"},{"v":"1486.74\r\n"}]},{"c":[{"v":"Date(2015,07,16)"},{"v":"1481.26\r\n"}]},{"c":[{"v":"Date(2015,07,17)"},{"v":"1479.31\r\n"}]},{"c":[{"v":"Date(2015,07,20)"},{"v":"1466.71\r\n"}]},{"c":[{"v":"Date(2015,07,21)"},{"v":"1447.44\r\n"}]},{"c":[{"v":"Date(2015,07,22)"},{"v":"1447.84\r\n"}]},{"c":[{"v":"Date(2015,07,23)"},{"v":"1444.66\r\n"}]},{"c":[{"v":"Date(2015,07,24)"},{"v":"1438.08\r\n"}]},{"c":[{"v":"Date(2015,07,27)"},{"v":"1412.55\r\n"}]},{"c":[{"v":"Date(2015,07,28)"},{"v":"1408.07\r\n"}]},{"c":[{"v":"Date(2015,07,29)"},{"v":"1417.49\r\n"}]},{"c":[{"v":"Date(2015,07,31)"},{"v":"1440.12\r\n"}]},{"c":[{"v":"Date(2015,08,03)"},{"v":"1442.04\r\n"}]},{"c":[{"v":"Date(2015,08,04)"},{"v":"1432.16\r\n"}]},{"c":[{"v":"Date(2015,08,05)"},{"v":"1436.36\r\n"}]},{"c":[{"v":"Date(2015,08,06)"},{"v":"1430.58\r\n"}]},{"c":[{"v":"Date(2015,08,07)"},{"v":"1428.79\r\n"}]},{"c":[{"v":"Date(2015,08,10)"},{"v":"1420.13\r\n"}]},{"c":[{"v":"Date(2015,08,11)"},{"v":"1408.32\r\n"}]},{"c":[{"v":"Date(2015,08,13)"},{"v":"1404.15\r\n"}]},{"c":[{"v":"Date(2015,08,14)"},{"v":"1413.92\r\n"}]},{"c":[{"v":"Date(2015,08,17)"},{"v":"1408.74\r\n"}]},{"c":[{"v":"Date(2015,08,18)"},{"v":"1372.61\r\n"}]},{"c":[{"v":"Date(2015,08,19)"},{"v":"1379.12\r\n"}]},{"c":[{"v":"Date(2015,08,20)"},{"v":"1372.53\r\n"}]},{"c":[{"v":"Date(2015,08,21)"},{"v":"1365.61\r\n"}]},{"c":[{"v":"Date(2015,08,24)"},{"v":"1301.06\r\n"}]},{"c":[{"v":"Date(2015,08,25)"},{"v":"1323.88\r\n"}]},{"c":[{"v":"Date(2015,08,26)"},{"v":"1320.08\r\n"}]},{"c":[{"v":"Date(2015,08,27)"},{"v":"1358.03\r\n"}]},{"c":[{"v":"Date(2015,08,28)"},{"v":"1365.94\r\n"}]},{"c":[{"v":"Date(2015,08,31)"},{"v":"1382.41\r\n"}]},{"c":[{"v":"Date(2015,09,01)"},{"v":"1362.39\r\n"}]},{"c":[{"v":"Date(2015,09,02)"},{"v":"1372.45\r\n"}]},{"c":[{"v":"Date(2015,09,03)"},{"v":"1383.48\r\n"}]},{"c":[{"v":"Date(2015,09,04)"},{"v":"1370.75\r\n"}]},{"c":[{"v":"Date(2015,09,07)"},{"v":"1371.4\r\n"}]},{"c":[{"v":"Date(2015,09,08)"},{"v":"1379.32\r\n"}]},{"c":[{"v":"Date(2015,09,09)"},{"v":"1396.29\r\n"}]},{"c":[{"v":"Date(2015,09,10)"},{"v":"1396.16\r\n"}]},{"c":[{"v":"Date(2015,09,11)"},{"v":"1381.72\r\n"}]},{"c":[{"v":"Date(2015,09,14)"},{"v":"1377.15\r\n"}]},{"c":[{"v":"Date(2015,09,15)"},{"v":"1370.65\r\n"}]},{"c":[{"v":"Date(2015,09,16)"},{"v":"1381.8\r\n"}]},{"c":[{"v":"Date(2015,09,17)"},{"v":"1389.7\r\n"}]},{"c":[{"v":"Date(2015,09,18)"},{"v":"1390.32\r\n"}]},{"c":[{"v":"Date(2015,09,21)"},{"v":"1392.73\r\n"}]},{"c":[{"v":"Date(2015,09,22)"},{"v":"1379.32\r\n"}]},{"c":[{"v":"Date(2015,09,23)"},{"v":"1375.17\r\n"}]},{"c":[{"v":"Date(2015,09,24)"},{"v":"1372.35\r\n"}]},{"c":[{"v":"Date(2015,09,25)"},{"v":"1376.83\r\n"}]},{"c":[{"v":"Date(2015,09,28)"},{"v":"1352.13\r\n"}]},{"c":[{"v":"Date(2015,09,29)"},{"v":"1348.84\r\n"}]},{"c":[{"v":"Date(2015,09,30)"},{"v":"1349\r\n"}]},{"c":[{"v":"Date(2015,10,01)"},{"v":"1345.15\r\n"}]},{"c":[{"v":"Date(2015,10,02)"},{"v":"1346.35\r\n"}]},{"c":[{"v":"Date(2015,10,05)"},{"v":"1363.17\r\n"}]},{"c":[{"v":"Date(2015,10,06)"},{"v":"1370.69\r\n"}]},{"c":[{"v":"Date(2015,10,07)"},{"v":"1393.66\r\n"}]},{"c":[{"v":"Date(2015,10,08)"},{"v":"1392.15\r\n"}]},{"c":[{"v":"Date(2015,10,09)"},{"v":"1411.33\r\n"}]},{"c":[{"v":"Date(2015,10,12)"},{"v":"1412.49\r\n"}]},{"c":[{"v":"Date(2015,10,13)"},{"v":"1406.69\r\n"}]},{"c":[{"v":"Date(2015,10,14)"},{"v":"1405.08\r\n"}]},{"c":[{"v":"Date(2015,10,15)"},{"v":"1425.32\r\n"}]},{"c":[{"v":"Date(2015,10,16)"},{"v":"1418.38\r\n"}]},{"c":[{"v":"Date(2015,10,19)"},{"v":"1416.91\r\n"}]},{"c":[{"v":"Date(2015,10,20)"},{"v":"1418.63\r\n"}]},{"c":[{"v":"Date(2015,10,21)"},{"v":"1415.8\r\n"}]},{"c":[{"v":"Date(2015,10,22)"},{"v":"1416.14\r\n"}]},{"c":[{"v":"Date(2015,10,26)"},{"v":"1424.16\r\n"}]},{"c":[{"v":"Date(2015,10,27)"},{"v":"1424.05\r\n"}]},{"c":[{"v":"Date(2015,10,28)"},{"v":"1409.26\r\n"}]},{"c":[{"v":"Date(2015,10,29)"},{"v":"1390.04\r\n"}]},{"c":[{"v":"Date(2015,10,30)"},{"v":"1394.94\r\n"}]},{"c":[{"v":"Date(2015,11,02)"},{"v":"1413.34\r\n"}]}]}